pyblhost/__init__.py
pyblhost/__main__.py
pyblhost/logger.py
pyblhost/py.typed
pyblhost/pyblhost.py
pyblhost-1.7.1.dist-info/WHEEL
pyblhost-1.7.1.dist-info/entry_points.txt
pyblhost-1.7.1.dist-info/METADATA
pyblhost-1.7.1.dist-info/RECORD
