Metadata-Version: 2.3
Name: pyblhost
Version: 1.7.1
Summary: Python implementation of blhost used to communicate with the NXP MCUBOOT/KBOOT bootloader
Keywords: blhost,kboot,bootloader,embedded,CAN,serial
Author: Kristian Sloth Lauszus
Author-email: Kristian Sloth Lauszus <lauszus@gmail.com>
License:                     GNU GENERAL PUBLIC LICENSE
Classifier: Programming Language :: Python :: 3
Classifier: License :: OSI Approved :: GNU General Public License v3 (GPLv3)
Classifier: Operating System :: OS Independent
Requires-Dist: tqdm
Requires-Dist: python-can>=4.3.0
Requires-Dist: pyserial
Requires-Python: >=3.9
Project-URL: Issues, https://github.com/Lauszus/pyblhost/issues
Project-URL: Repository, https://github.com/Lauszus/pyblhost
